envsugar/__init__.py
envsugar-0.1.0.dist-info/WHEEL
envsugar-0.1.0.dist-info/METADATA
envsugar-0.1.0.dist-info/RECORD
