Metadata-Version: 2.4
Name: envsugar
Version: 0.1.0
Summary: A simple package to make getting env vars syntactically nicer
Author: Sychic
License-Expression: MIT
Requires-Python: >=3.13
